odoo/addons/l10n_us_form_1099/README.rst
odoo/addons/l10n_us_form_1099/__init__.py
odoo/addons/l10n_us_form_1099/__manifest__.py
odoo/addons/l10n_us_form_1099/i18n/nl_NL.po
odoo/addons/l10n_us_form_1099/models/__init__.py
odoo/addons/l10n_us_form_1099/models/res_partner.py
odoo/addons/l10n_us_form_1099/static/description/icon.png
odoo/addons/l10n_us_form_1099/static/description/l10n_us_form_1099.svg
odoo/addons/l10n_us_form_1099/tests/__init__.py
odoo/addons/l10n_us_form_1099/tests/test_l10n_us_form_1099.py
odoo/addons/l10n_us_form_1099/views/res_partner.xml
odoo11_addon_l10n_us_form_1099-11.0.1.0.0.dist-info/DESCRIPTION.rst
odoo11_addon_l10n_us_form_1099-11.0.1.0.0.dist-info/METADATA
odoo11_addon_l10n_us_form_1099-11.0.1.0.0.dist-info/RECORD
odoo11_addon_l10n_us_form_1099-11.0.1.0.0.dist-info/WHEEL
odoo11_addon_l10n_us_form_1099-11.0.1.0.0.dist-info/metadata.json
odoo11_addon_l10n_us_form_1099-11.0.1.0.0.dist-info/top_level.txt
